{"채굴":[{"1":[["採掘"],[["땅을 파고 땅속에 묻혀 있는 광물 따위를 캐냄.","없음"]],3,"채ː굴"]},{"0":[["採掘"],[["mining","An act of extracting metals, minerals, etc., from the ground. "]],0,"채ː굴"]}],"책상다리황새두렁넘기":[{"1":[["冊床"],[["줄타기 재주의 하나. 책상다리를 한 채 무릎을 꿇고 걸어 나간다.","민속"]],1,"책쌍다리황새두렁넘끼"]},{}],"채운":[{"1":[["彩雲"],[["상서로운 구름.",null],["여러 빛깔로 아롱진 고운 구름. 구름을 이루는 물방울이나 얼음 결정에 빛이 회절되어 고운 빛깔로 물들어 보인다.","지구"]],3,"채ː운"]},{}],"책례":[{"1":[["冊禮"],[["글방 따위에서 학생이 책 한 권을 다 읽어 떼거나 다 베껴 쓰고 난 뒤에 선생과 동료들에게 한턱내는 일.",null]],3,"챙녜"],"2":[["冊禮"],[["왕세자를 책봉(冊封)하던 예식.","역사"]],3,"챙녜"]},{}],"채표":[{"1":[["彩票"],[["예전에, 일정한 액수로 표를 많이 발행하여 제비로 뽑은 몇 사람에게 차등이 있게 태워 주던 일. 또는 그런 표.",null]],3,"채ː표"]},{}],"채신지우":[{"1":[["採薪之憂"],[["땔나무를 할 수 없는 근심이라는 뜻으로, 병환을 이르는 말. ≪맹자≫의 <공손추편>에 나오는 말이다.",null]],3,"채ː신지우"]},{}],"채롱":[{"1":[["籠"],[["껍질을 벗긴 싸릿개비나 버들가지 따위의 오리를 결어서 함(函) 모양으로 만든 채그릇. 안팎에 종이를 바르기도 한다.",null]],1,"채롱"],"2":[["綵籠"],[["아름다운 색깔로 꾸민 바구니.",null]],3,"채ː롱"]},{}],"책언":[{"1":[["責言"],[["꾸짖거나 나무라는 말.",null]],3,"채건"]},{}],"챌낚시":[{"1":[[],[["낚싯줄을 잡아채어 물고기를 낚는 일.",null]],2,"챌락씨"]},{}],"채달":[{"1":[["菜疸"],[["채소 따위에 중독되어 생기는 황달.","한의"]],3,"채ː달"]},{}],"채륵":[{"1":[["債勒"],[["조선 시대에, 이채(吏債)ㆍ저채(邸債)를 환곡과 함께 거두어들이던 일.","역사"]],3,"채ː륵"]},{}],"챌면":[{"1":[["面"],[["계단 한 단의 수직면.","건설"]],1,"챌면"]},{}],"챗국":[{"1":[[],[["무, 오이 따위의 채로 만든 국. 또는 그렇게 만든 냉국.",null]],2,"채ː꾹"]},{}],"책궁":[{"1":[["責躬"],[["스스로 자신을 나무람.",null]],3,"책꿍"]},{}],"채조":[{"1":[["綵組"],[["빛깔이 고운 실로 꼰 끈.",null]],3,"채ː조"]},{}],"채마":[{"1":[["菜麻"],[["먹을거리나 입을 거리로 심어서 가꾸는 식물.",null],["채마를 심어 가꾸는 밭.",null]],3,"채ː마"]},{}],"채필":[{"1":[["彩筆"],[["채색할 때에 쓰는 붓.",null]],3,"채ː필"]},{}],"채금업자":[{"1":[["採金業者"],[["금을 캐는 사업을 하는 사람.",null]],3,"채ː그멉짜"]},{}],"책씻이":[{"1":[["冊"],[["글방 따위에서 학생이 책 한 권을 다 읽어 떼거나 다 베껴 쓰고 난 뒤에 선생과 동료들에게 한턱내는 일.",null]],1,"책씨시"]},{}],"채권자":[{"1":[["債權者"],[["특정인에게 일정한 빚을 받아 낼 권리를 가진 사람.","법률"]],3,"채ː꿘자"]},{"0":[["債權者"],[["creditor","A person who has the right to collect a debt from someone. "]],0,"채ː꿘자"]}],"책벌":[{"1":[["責罰"],[["저지른 잘못이나 죄를 꾸짖어 벌을 줌. 또는 그 벌.",null]],3,"책뻘"]},{}],"채탐":[{"1":[["採探"],[["모르는 곳을 더듬어 살핌. 또는 그렇게 하여 찾아감.",null]],3,"채ː탐"]},{}],"채국":[{"1":[["彩菊"],[["동양화에서, 채색하여 그린 국화.","미술"]],3,"채ː국"]},{}],"채근":[{"1":[["採根"],[["식물의 뿌리를 캐냄.",null],["어떤 일의 내용, 원인, 근원 따위를 캐어 알아냄.",null],["어떻게 행동하기를 따지어 독촉함.",null],["남에게 받을 것을 달라고 독촉함.",null]],3,"채ː근"],"2":[["菜根"],[["먹을 수 있는 채소의 뿌리.",null],["맛없고 거칠고 보잘것없는 음식을 비유적으로 이르는 말.",null]],3,"채ː근"]},{"0":[["採根"],[["root dig","An act of digging up the roots of a plant."],["tracing back","An act of finding out the facts, causes, etc., of something."],["urge","An act of pushing someone to do something quickly."],["urge","An act of pushing someone to return something borrowed quickly."]],0,"채ː근"]}],"채석":[{"1":[["採石"],[["돌산이나 바위에서 석재(石材)로 쓸 돌을 캐거나 떠 냄.",null],["취미로 돌을 채집함.",null]],3,"채ː석"]},{"0":[["採石"],[["quarrying","An act of digging or cutting useful stones or rocks from a quarry."]],0,"채ː석"]}],"책판":[{"1":[["冊板"],[["책을 박아 내는 판.",null]],3,"책판"]},{}],"채독":[{"1":[[],[["싸릿개비나 버들가지 따위의 오리를 결어 독 모양으로 만들고 안팎으로 종이를 바른 채그릇. 산간 지방에서 마른 곡식을 갈무리할 때에 많이 쓴다.",null]],2,"채독"],"2":[["菜毒"],[["채소 따위에 섞여 있는, 채독증을 일으키는 독기.",null],["구충에 감염되었을 때 나타나는 여러 가지 증상. 목구멍이 가렵고 기침을 하며 얼굴이 누렇게 붓고 오심(惡心), 구토, 설사 따위를 하게 된다.","의학"]],3,"채ː독"]},{}],"채봉감별곡":[{"1":[["彩鳳感別曲"],[["조선 시대의 장회 소설. 평양 김 진사의 딸 채봉과 선천 부사의 아들 강필성이 많은 시련을 극복하고 혼인하게 되는 이야기이다. 작가와 연대는 알 수 없다.","문학"]],3,"채ː봉감별곡"]},{}],"채썰기":[{"1":[[],[["야채나 과일 따위를 가늘고 길쭉하게 잘게 써는 방법.",null]],2,"채ː썰기"]},{}],"채주":[{"1":[["採珠"],[["바닷물 속에 들어가 진주를 캐어 냄.",null]],3,"채ː주"],"2":[["債主"],[["남에게 돈을 빌려준 사람.",null]],3,"채ː주"]},{}],"책성":[{"1":[["柵城"],[["성(城)에 둘러친 울짱.",null]],3,"책썽"],"2":[["責成"],[["남에게 맡긴 일이 잘되도록 다짐을 받음.",null],["일의 책임과 부담을 지움.",null]],3,"책썽"]},{}],"책가방":[{"1":[["冊"],[["주로 학생들이 책이나 학용품 따위를 넣어서 들거나 메고 다니는 가방.",null]],1,"책까방"]},{"0":[["冊가방"],[["student backpack; student bag","A bag designed mainly for students to carry books, notebooks, pencil cases, etc., on the back or shoulder."]],2,"책까방"]}],"채반":[{"1":[[],[["→ 차반01.",null]],2,null],"2":[["盤"],[["껍질을 벗긴 싸릿개비나 버들가지 따위의 오리를 울과 춤이 거의 없이 둥글넓적하게 결어 만든 채그릇.",null],["새색시가 근친을 갈 때나, 시집에 올 때 해 오는 음식.",null]],1,"채반"],"3":[["菜飯"],[["무 따위의 채소를 섞은 밥이라는 뜻으로, 변변하지 못한 음식을 이르는 말.",null]],3,"채ː반"]},{"0":[["채盤"],[["wicker tray","A container made by splitting bush clover, bamboo, etc., thinly and weaving the strips into a round, flat tray."]],0,"채반"]}],"책상다리가새틀음":[{"1":[["冊床"],[["줄타기 재주의 하나. 책상다리를 하였다가 솟구쳐 몸을 틀어 앉으면서 다시 책상다리를 한다.","민속"]],1,"책쌍다리가새트름"]},{}],"책략":[{"1":[["策略"],[["어떤 일을 꾸미고 이루어 나가는 교묘한 방법.",null]],3,"챙냑"]},{"0":[["策略"],[["trick; scheme","A clever way of plotting or solving something. "]],0,"챙냑"]}],"책빈":[{"1":[["冊嬪"],[["빈(嬪)을 봉하여 세우던 일.","역사"]],3,"책삔"]},{}],"채공":[{"1":[["採工"],[["광물, 돌 따위를 캐는 사람.",null]],3,"채ː공"],"2":[["菜供"],[["절에서, 부식물을 만들거나 그 재료인 야채를 관리하는 일. 또는 그런 사람.","불교"]],3,"채ː공"]},{}],"채하":[{"1":[["彩霞"],[["빛이 아름다운 노을.",null]],3,"채ː하"]},{}],"책가":[{"1":[["冊"],[["책의 가장자리.",null]],1,"책까"],"2":[["冊價"],[["책을 파는 값.",null]],3,"책까"]},{}],"채식":[{"1":[["彩飾"],[["아름다운 빛깔을 칠하여 꾸미는 일.",null]],3,"채ː식"],"2":[["菜食"],[["고기류를 피하고 주로 채소, 과일, 해초 따위의 식물성 음식만 먹음.",null]],3,"채ː식"]},{"0":[["菜食"],[["vegetarian diet","A selection of plant-based food consisting of vegetables, fruits, seaweed, etc., rather than meat."]],3,"채ː식"]}],"채터바":[{"1":[[],[["자동차가 빨리 달리지 못하도록 길바닥을 울퉁불퉁하게 만든 노면(路面) 시설물. 주택가의 길이나 톨게이트 바로 앞 도로에 설치한다.","교통"]],4,null]},{}],"채유":[{"1":[["採油"],[["유전(油田)에서 석유를 땅속으로부터 뽑아내는 일.","광업"],["식물의 씨에서 기름을 짬.",null]],3,"채ː유"],"2":[["菜油"],[["채소의 씨로 짠 기름.",null],["배추씨로 짠 기름.",null]],3,"채ː유"]},{}],"채취":[{"1":[["採取"],[["풀, 나무, 광석 따위를 찾아 베거나 캐거나 하여 얻어 냄.",null],["연구나 조사에 필요한 것을 찾거나 받아서 얻음.",null]],3,"채ː취"]},{"0":[["採取"],[["collection; gathering","An act of getting something from nature by cutting or digging."],["collection","An act of finding and getting something necessary for a research or investigation."]],0,"채ː취"]}],"책궤":[{"1":[["冊櫃"],[["책을 넣어 두는 궤짝.",null]],3,"책꿰"]},{}],"책엽":[{"1":[["冊葉"],[["책을 이루고 있는 낱낱의 장.",null]],3,"채겹"]},{}],"채터누가":[{"1":[[],[["미국 테네시주 동남부에 있는 공업 도시. 남북 전쟁 때의 격전지였으며, 전적 공원이 있다. 티브이에이(TVA) 계획의 중심지로 기계, 섬유, 원자력 따위의 공업이 발달하였다.","지명"]],4,null]},{}],"책사":[{"1":[["冊絲"],[["책을 매는 데 쓰는 실.",null]],3,"책싸"],"2":[["冊肆"],[["책을 갖추어 놓고 팔거나 사는 가게.","없음"]],3,"책싸"],"3":[["策士"],[["꾀를 써서 일이 잘 이루어지게 하는 사람.",null],["남을 도와 꾀를 내는 사람.",null]],3,"책싸"]},{}],"채구":[{"1":[["彩毬"],[["궁중에서, 포구락(抛毬樂)을 연주할 때 던지던 나무로 만든 공.","무용"],["격구(擊毬), 타구(打毬), 모구(毛毬)를 할 때 쓰는 공. 나무, 마노(瑪瑙), 녹비, 저피(豬皮) 따위로 만든다.","체육"]],3,"채ː구"],"2":[["彩球"],[["태양의 광구(光球)와 상층 대기인 코로나 사이의 대기층. 두께는 약 1,600km이며, 일식(日蝕) 때 코로나의 아래층에서 분홍빛으로 보인다.","천문"]],3,"채ː구"]},{}],"책비":[{"1":[["冊妃"],[["비빈(妃嬪)으로 책봉하던 일.","역사"]],3,"책삐"],"2":[["責備"],[["남에게 모든 일을 완전하게 갖추어 다 잘하기를 요구함.",null]],3,"책삐"]},{}],"채플":[{"1":[[],[["기독교 계통의 학교 따위에서 행하는 예배 모임.",null]],4,null]},{"0":[["chapel"],[["chapel","A worship gathering that takes place in a Christian school."]],0,null]}],"채단":[{"1":[["采緞"],[["혼인 때에, 신랑집에서 신붓집으로 미리 보내는 푸른색과 붉은색의 비단. 치마나 저고릿감으로 쓴다.","민속"]],3,"채ː단"],"2":[["彩團"],[["조선 시대에, 가무와 곡예에 종사하는 사람들로 이루어진 농민 폭동 조직.","역사"]],3,"채ː단"],"3":[["菜單"],[["중국요리의 식단.",null]],3,"채ː단"],"4":[["綵緞"],[["온갖 비단을 통틀어 이르는 말.",null]],3,"채ː단"]},{}],"채각":[{"1":[["彩閣"],[["아름답게 단청한 누각.",null]],3,"채ː각"]},{}],"채전":[{"1":[["彩典"],[["신라 때에, 그림에 관한 일을 맡아보던 관아. 경덕왕 때 전채서로 고쳤다.","역사"]],3,"채ː전"],"2":[["彩牋","采箋"],[["시를 지어 쓰는 데 쓰는 무늬 있는 색종이.",null]],3,"채ː전"],"3":[["菜田"],[["채소를 심어 가꾸는 밭.",null]],3,"채ː전"],"4":[["債錢"],[["남에게 빚진 돈.",null]],3,"채ː전"]},{}],"채움재":[{"1":[["材"],[["광석이나 석탄을 캔 공간이 무너지지 않도록 하기 위하여 채우는 재료. 강모래, 흙 따위를 쓴다.","광업"]],1,"채움재"]},{}],"책임":[{"1":[["責任"],[["맡아서 해야 할 임무나 의무.",null],["어떤 일에 관련되어 그 결과에 대하여 지는 의무나 부담. 또는 그 결과로 받는 제재(制裁).",null],["위법한 행동을 한 사람에게 법률적 불이익이나 제재를 가하는 일. 민사 책임과 형사 책임이 있다.","법률"]],3,"채김"]},{"0":[["責任"],[["duty; responsibility; obligation","A task or duty that one is responsible for."],["responsibility","An obligation or burden that one has from the result of something, or the disadvantage that follows such a result."],["responsibility","An act of giving a legal disadvantage or restriction to the person who broke a law."]],2,"채김"]}],"책갑":[{"1":[["冊甲"],[["책의 겉장이 상하지 아니하게 종이, 비닐, 헝겊 따위로 덧씌우는 일. 또는 그런 물건.",null]],3,"책깝"],"2":[["冊匣"],[["책을 넣어 둘 수 있게 책의 크기에 맞추어 만든 작은 상자나 집.",null]],3,"책깝"]},{}],"챙피":[{"1":[[],[["→ 창피.",null]],2,null]},{}],"책모":[{"1":[["策謀"],[["어떤 일을 꾸미고 이루어 나가는 교묘한 생각.",null]],3,"챙모"]},{}],"챗고리":[{"1":[[],[["가늘고 긴 채의 앞머리에 달린 고리.",null]],2,"채꼬리"]},{}],"채층":[{"1":[["彩層"],[["태양의 광구(光球)와 상층 대기인 코로나 사이의 대기층. 두께는 약 1,600km이며, 일식(日蝕) 때 코로나의 아래층에서 분홍빛으로 보인다.","천문"]],3,"채ː층"]},{}],"책임량":[{"1":[["責任量"],[["책임지고 하여야 할 양.",null]],3,"채김냥"]},{"0":[["責任量"],[["amount of duty","The amount of work assigned to someone."]],0,"책임냥"]}],"채정":[{"1":[["採精"],[["인공 수정 따위를 하기 위하여 정액을 채취하여 모음.","의학"]],3,"채ː정"]},{}],"채련":[{"1":[[],[["부드럽게 다루어 만든 당나귀 가죽.",null]],2,"채련"],"2":[["鍊"],[["→ 초련02.",null]],1,null],"3":[["彩輦"],[["왕실의 의식 때 귀중품을 싣던 꽃무늬를 놓은 가마.","역사"]],3,"채ː련"],"4":[["採蓮"],[["연을 캐거나 땀.",null]],3,"채ː련"],"5":[["採鍊"],[["광물을 캐내어 정련하는 일.","공업"]],3,"채ː련"]},{}],"채수":[{"1":[["菜"],[["→ 채소.",null]],1,null],"2":[["採水"],[["강물이나 바닷물의 물리적ㆍ화학적 특성을 연구하기 위하여 서로 다른 깊이의 물을 떠올리는 일.",null]],3,"채ː수"],"3":[["採收"],[["석유가 괴어 있는 지층으로부터 원유나 가스 따위를 땅 위로 뽑아내는 일.","광업"]],3,"채ː수"]},{}],"채양":[{"1":[["陽"],[["→ 차양02「1」.","건설"]],1,null]},{}],"책문":[{"1":[["冊文"],[["간책(簡冊)에 새기는 글.",null]],3,"챙문"],"2":[["柵門"],[["말뚝으로 만든 우리나 울타리의 문.",null]],3,"챙문"],"3":[["責問"],[["꾸짖거나 나무라며 물음.",null]],3,"챙문"],"4":[["策文"],[["책문(策問)에 답하던 글.","역사"],["임금이 신하에게 내려서 명령하던 글발.","역사"]],3,"챙문"],"5":[["策問"],[["정치에 관한 계책을 물어서 답하게 하던 과거(科擧) 과목.","역사"]],3,"챙문"]},{}],"채류":[{"1":[["菜類"],[["채소나 나물 따위의 부류.",null]],3,"채ː류"]},{}],"채판":[{"1":[["彩板"],[["단청을 하거나 그림을 그릴 때에, 화공(畫工)들이 쓸 수 있게 여러 가지 채색을 만들어서 벌여 풀어 놓은 판.",null]],3,"채ː판"]},{}],"책걸상":[{"1":[["冊","床"],[["책상과 걸상을 아울러 이르는 말.",null],["책상과 걸상이 한데 붙은 집기.",null]],1,"책껄쌍"]},{"0":[["冊걸床"],[["desks and chairs","Desks and desk chairs."]],0,"책껄상"]}],"채받이":[{"1":[[],[["소가 채를 늘 맞는 부위의 가죽이나 고기. 소의 등심 끝머리 부분에 해당한다.",null]],2,"채바지"]},{}],"책":[{"1":[["冊"],[["종이를 여러 장 묶어 맨 물건.",null],["일정한 목적, 내용, 체재에 맞추어 사상, 감정, 지식 따위를 글이나 그림으로 표현하여 적거나 인쇄하여 묶어 놓은 것.",null],["옛 서적이나 여러 장의 종이를 하나로 묶은 것을 세는 단위.",null],["‘서적’임을 나타내는 말.",null]],3,"책"],"2":[["柵"],[["말뚝으로 만든 우리나 울타리.",null],["물결에 둑이 넘어지지 않게 하기 위하여 둑 앞에 말뚝을 듬성듬성 박고 대쪽으로 얽어 놓는 장치.",null]],3,"책"],"3":[["責"],[["잘못을 꾸짖거나 나무라며 못마땅하게 여김.",null],["맡아서 해야 할 임무나 의무.",null],["어떤 일에 관련되어 그 결과에 대하여 지는 의무나 부담. 또는 그 결과로 받는 제재(制裁).",null]],3,"책"],"4":[["策"],[["정치에 관한 계책을 물어서 답하게 하던 과거(科擧) 과목.","역사"]],3,"책"],"5":[["策"],[["‘채편’을 달리 이르는 말.","음악"]],3,"책"],"7":[["幘"],[["삼국 시대 이후에 무관들이 주로 쓰던 모자. 모자 테의 윗부분을 덧대었는데 앞이 낮고 뒷부분이 높으며 두 가닥으로 갈라지면서 앞으로 구부러졌다.","역사"]],3,"책"]},{"0":[["冊"],[["books; publications","Pieces of writing, pictures, etc., that are printed and bound."],["volume","A unit for counting the number of old books or several pages of paper bound into one."],["book","A word used to indicate &quot;a book.&quot;"]],1,"책"]}],"채목장":[{"1":[["採木場"],[["예전에, 목재를 생산하는 산판을 이르던 말.",null]],3,"채ː목짱"]},{}],"채홍준사":[{"1":[["採紅駿使"],[["조선 연산군 때에, 아름다운 처녀와 좋은 말을 구하려고 지방에 보내던 벼슬아치.","역사"]],3,"채ː홍준사"]},{}],"채협":[{"1":[["彩篋"],[["대나무를 가늘게 쪼개어 채색한 무늬를 놓아 만든 상자.",null]],3,"채ː협"]},{}],"책침":[{"1":[["責侵"],[["간접적으로 관계되는 사람에게 책임을 추궁함.",null]],3,"책침"]},{}],"채색화":[{"1":[["彩色畫"],[["색을 칠하여 그린 그림.","미술"]],3,"채ː새콰"]},{"0":[["彩色畫"],[["painting","A picture painted with color."]],0,"채ː새콰 "]}],"채로":[{"1":[["菜露"],[["선원에서, 국을 끓이는 소임. 또는 그 소임을 맡은 사람.","불교"]],3,"채ː로"]},{}],"채벌":[{"1":[["採伐"],[["나무를 베어 내거나 섶을 깎아 냄.",null]],3,"채ː벌"]},{}],"책갈피":[{"1":[["冊"],[["책장과 책장의 사이.",null],["읽던 곳이나 필요한 곳을 찾기 쉽도록 책의 낱장 사이에 끼워 두는 물건을 통틀어 이르는 말.",null]],1,"책깔피"]},{"0":[["冊갈피"],[["(no equivalent expression)","Space between the pages of a book."],["bookmark; bookmarker","A piece of material placed between the pages of a book so that the part the reader has been reading or wants to read can be accessed easily."]],0,"책깔피"]}],"채료":[{"1":[["彩料"],[["그림을 그리는 데 쓰는 모든 물감.","미술"]],3,"채ː료"]},{}],"책상머리":[{"1":[["冊床"],[["책상의 한쪽 자리.",null]],1,"책쌍머리"]},{"0":[["冊床머리"],[["desk","A part of the desk."]],0,"책쌍머리"]}],"책유":[{"1":[["責諭"],[["임금이 신하의 잘못을 문책하여 내리는 글.",null]],3,"채규"]},{}],"채묵":[{"1":[["彩墨"],[["그림을 그릴 때에, 먹처럼 갈아서 쓰도록 채색감을 단단하게 뭉친 조각.","미술"]],3,"채ː묵"]},{}],"책객":[{"1":[["冊客"],[["고을 원의 비서 일을 맡아보던 사람. 관제(官制)에는 없는데 사사로이 임용하였다.","역사"]],3,"책깩"]},{}],"채끝":[{"1":[[],[["소 등심 부분의 방아살 아래에 붙은 쇠고기 부위.",null]],2,"채끋"]},{}],"책망":[{"1":[["責望"],[["잘못을 꾸짖거나 나무라며 못마땅하게 여김.",null]],3,"챙망"]},{"0":[["責望"],[["scold; reproach; rebuke","An act of scolding or blaming a person for his/her fault."]],0,"챙망"]}],"채혈":[{"1":[["採血"],[["병의 진단이나 수혈 따위를 위하여 피를 뽑는 일.","의학"]],3,"채ː혈"]},{}],"채적":[{"1":[["採摘"],[["잎 따위를 땀.",null]],3,"채ː적"]},{}],"책무":[{"1":[["責務"],[["직무에 따른 책임이나 임무.",null]],3,"챙무"]},{"0":[["責務"],[["duty; obligation","A task or duty that one is responsible for."]],0,"챙무"]}],"채귀":[{"1":[["債鬼"],[["악착같이 이자를 받고 빚 갚기를 몹시 졸라 대는 빚쟁이를 비유적으로 이르는 말.",null]],3,"채ː귀"]},{}],"채등":[{"1":[["彩燈"],[["아름답게 빛깔을 들인 등.",null]],3,"채ː등"]},{}],"채비":[{"1":[[],[["어떤 일이 되기 위하여 필요한 물건, 자세 따위가 미리 갖추어져 차려지거나 그렇게 되게 함. 또는 그 물건이나 자세.",null]],2,"채비"]},{"0":[[],[["preparation; readiness","A state in which objects, attitude, etc., necessary to do something are prepared in advance or an act of preparing such things in advance; such objects or attitude. "]],0,"채비"]}],"챌목매":[{"1":[[],[["짐승이 건드리면 목이나 다리를 옭아 공중에 달아 올리게 만든 올무.",null]],2,"챌몽매"]},{}],"책원":[{"1":[["策源"],[["전방 부대에 보급, 정비, 위생 따위의 병참 지원을 행하는 후방 기지.","군사"]],3,"채권"]},{}],"채난":[{"1":[["採暖"],[["따뜻한 기운을 몸속에 빨아들임.",null]],3,"채ː난"]},{}],"채숭아":[{"1":[["菜"],[["→ 채송화.","식물"]],1,null]},{}],"채갱":[{"1":[["菜羹"],[["나물을 넣고 끓인 국.",null]],3,"채ː갱"]},{}],"챌린저호":[{"1":[["號"],[["미국의 유인 우주 왕복선 제2호기. 1983년 4월부터 8월 사이에 세 차례 비행하였다.","천문"]],1,null],"2":[["號"],[["영국의 해양 조사선. 8세호와 6세호가 있으며, 1951년 8세호가 챌린저 해연을 발견하였다.","해양"]],1,null]},{}],"책임자":[{"1":[["責任者"],[["어떤 일에 대하여 책임을 지고 있거나 책임을 져야 할 위치에 있는 사람.",null]],3,"채김자"]},{"0":[["責任者"],[["person in charge","A person who is responsible for something, or in the position to be responsible."]],2,"채김자"]}],"채권":[{"1":[["債券"],[["남에게 빌린 돈의 금액을 적는 장부.",null],["국가, 지방 자치 단체, 은행, 회사 따위가 사업에 필요한 자금을 차입하기 위하여 발행하는 유가 증권. 공채, 국채, 사채, 지방채 따위가 있다.","경제"]],3,"채ː꿘"],"2":[["債權"],[["재산권의 하나. 특정인이 다른 특정인에게 어떤 행위를 청구할 수 있는 권리이다.","법률"]],3,"채ː꿘"]},{"0":[["債券"],[["bond; debenture","Securities issued in order for the government, a local government, bank, company, etc., to raise funds necessary for a project."]],0,"채ː꿘"]}],"채니관":[{"1":[["採泥管"],[["바다, 하천, 호수 따위의 바닥에서 모래나 감탕을 파 올리는 속이 굵은 기둥 모양의 관.",null]],3,"채ː니관"]},{}],"채봉":[{"1":[["彩棒"],[["격구에서, 공을 치고 받는 데 쓰던 막대기.","체육"]],3,"채ː봉"],"2":[["彩鳳","綵鳳"],[["빛깔이 곱고 아름다운 봉황새.",null]],3,"채ː봉"]},{}],"책값":[{"1":[["冊"],[["책을 파는 값.",null],["책을 사는 데 드는 돈.",null]],1,"책깝"]},{"0":[["冊값"],[["book price","The price of a book."],["expenses for books","Money spent on books."]],0,"책깝"]}],"채급":[{"1":[["債給"],[["남에게 돈을 꾸어 줌.",null]],3,"채ː급"]},{}],"채원":[{"1":[["菜園"],[["전문적으로 채소를 심어 가꾸는 규모가 큰 밭.",null]],3,"채ː원"]},{}],"챌판":[{"1":[["板"],[["계단의 디딤판과 디딤판 사이에 수직으로 댄 판.","건설"],["현관이나 출입이 빈번한 여닫이문의 아랫부분에 높이 30cm 안팎으로 댄 쇠붙이 판.","건설"]],1,"챌판"]},{}],"책받침":[{"1":[["冊"],[["글씨를 쓸 때에 아래 장에 자국이 나지 않고 잘 써지도록 종이 밑에 받치는 단단하고 판판한 물건.",null]],1,"책빧침"],"2":[["辵▽"],[["한자 부수의 하나. ‘갖은책받침(辵)’ 부수가 ‘近’, ‘造’ 따위에서 ‘辶’으로 쓰일 때의 이름이다.",null]],1,"책빧침"]},{"0":[["冊받침"],[["plastic sheet","A hard, flat sheet placed under a piece of paper when writing. "]],0,"책빧침"]}],"채화칠협":[{"1":[["彩畫漆篋"],[["낙랑 때의 공예품. 옻칠로 충신(忠臣), 열녀(烈女) 등을 그린 대나무 상자로, 1932년에 평양 부근 대동강 하류의 채협총에서 출토되었다.","역사"]],3,"채ː화칠협"]},{}],"책서":[{"1":[["冊書"],[["책장에 쓰는 잘고 깨끗한 글씨.",null],["책을 베끼어 씀.",null]],3,"책써"],"2":[["策書"],[["임금이 벼슬아치를 임명하던 사령장.","역사"]],3,"책써"]},{}],"채송화":[{"1":[["菜松花"],[["쇠비름과의 한해살이풀. 줄기는 높이가 20cm 정도이며, 분홍색이다. 잎은 어긋나고 육질이며 원기둥 모양이다. 여름에서 가을에 걸쳐 자주, 노랑, 분홍, 흰색의 꽃이 아침에 피었다가 오후에 시든다. 열매는 둥근 삭과(蒴果)이다. 관상용이고 남아메리카가 원산지이다.","식물"]],3,"채ː송화"]},{"0":[["菜松花"],[["rose moss","A flower that blooms during the summer and fall, blossoms in the morning and withers in the afternoon."]],0,"채ː송화"]}],"책보":[{"1":[["冊褓"],[["책을 싸는 보자기.",null]],3,"책뽀"],"2":[["冊寶"],[["왕이나 왕비의 존호를 올릴 때에 함께 올리던 옥책(玉冊)과 금보(金寶)를 아울러 이르는 말.","역사"]],3,"책뽀"],"3":[["責保"],[["높은 관원이 담당 관아의 관원 가운데서 재주가 많거나 특별한 공로가 있는 사람을 골라, 자신이 책임지고 임금에게 천거하던 일.","역사"],["죄인이나 혐의자를 책임지고 보석(保釋)하여 주던 일.","역사"]],3,"책뽀"]},{"0":[["冊褓"],[["wrapping cloth","A piece of fabric for wrapping books. "]],0,"책뽀"]}],"채소밭":[{"1":[["菜蔬"],[["채소를 심어 가꾸는 밭.",null]],1,"채ː소받"]},{"0":[["菜蔬밭"],[["vegetable field; vegetable garden","A field in which vegetables are planted and grown. "]],0,"채ː소받"]}],"채교":[{"1":[["彩轎"],[["채색을 하거나 채색 비단으로 꾸민 교자(轎子).",null]],3,"채ː교"]},{}],"채충":[{"1":[["蠆蟲"],[["전갈과의 하나. 몸의 길이는 3.5~20cm이며 누런색이다. 몸은 짧은 두흉부와 좁고 긴 배로 나뉘는데 꼬리 끝에 독침이 있다. 한국, 중국, 북아메리카, 열대 지방 등지에 분포한다.","동물"]],3,"채ː충"]},{}],"채청사":[{"1":[["採靑使"],[["조선 연산군 때에, 아름다운 처녀를 구하려고 전국에 보낸 벼슬아치.","역사"]],3,"채ː청사"]},{}],"채육":[{"1":[["採肉"],[["동물의 뼈나 껍데기에 붙은 살을 떼어 냄.",null]],3,"채ː육"],"2":[["菜肉"],[["채소류와 육류를 아울러 이르는 말.",null]],3,"채ː육"]},{}],"채화":[{"1":[["彩畫"],[["색을 칠하여 그린 그림.","미술"]],3,"채ː화"],"2":[["採火"],[["오목 거울이나 볼록 렌즈 따위로 태양 광선을 모아 받아서 불을 얻음.",null]],3,"채ː화"],"3":[["菜花"],[["채소의 꽃.",null]],3,"채ː화"],"4":[["綵花"],[["비단이나 모시, 종이 따위로 만든 꽃.",null]],3,"채ː화"]},{}],"책가우지":[{"1":[["冊"],[["→ 책가위.",null]],1,null]},{}],"채광":[{"1":[["彩光"],[["아름다운 색깔의 빛.",null]],3,"채ː광"],"2":[["採光"],[["창문 따위를 내어 햇빛을 비롯한 광선을 받아 들임.","없음"]],3,"채ː광"],"3":[["採鑛"],[["광석을 캐냄.","광업"]],3,"채ː광"]},{"0":[["採光"],[["lighting","The state of bringing in sunlight through a window, etc."]],0,"채ː광"]}],"챙":[{"1":[[],[["모자 끝에 대서 햇볕을 가리는 부분.",null],["햇볕을 가리거나 비가 들이치는 것을 막기 위하여 처마 끝에 덧붙이는 좁은 지붕.","건설"]],2,"챙ː"]},{"0":[[],[["bill; peak","A piece of fabric attached to the front of a cap to block sunlight."]],0,"챙ː"]}],"채프":[{"1":[[],[["상대편의 레이다 탐지를 방해하기 위하여 공중에 뿌리는 알루미늄 따위의 금속박(金屬箔).","화학"]],4,null]},{}],"채패업":[{"1":[["採貝業"],[["조개류를 잡는 어업.","수산업"]],3,"채ː패업"]},{}],"책화":[{"1":[["責禍"],[["동예에서, 마을 사이의 경계를 침입하였을 때에, 노예ㆍ소ㆍ말 따위로 배상하던 벌칙.","역사"]],3,"채콰"]},{}],"채염":[{"1":[["採鹽"],[["염전에서 소금을 채취함.",null]],3,"채ː염"]},{}],"챗날":[{"1":[[],[["기름틀 떡판에 올려놓은 기름떡을 덮어 눌러서 기름을 짜는, 길고 두꺼운 널판.",null]],2,"챈날"]},{}],"채송":[{"1":[["債訟"],[["채권이나 채무에 관한 소송(訴訟).","법률"]],3,"채ː송"]},{}],"채초":[{"1":[["採草"],[["집짐승의 먹이나 깃, 거름 따위로 쓰기 위하여 풀을 벰.",null]],3,"채ː초"],"2":[["採樵"],[["땔나무를 베어 두었다가 마른 뒤에 거둠.",null]],3,"채ː초"]},{}],"채척":[{"1":[["採摭"],[["뽑아서 가려냄.",null]],3,"채ː척"]},{}],"채택":[{"1":[["採擇"],[["작품, 의견, 제도 따위를 골라서 다루거나 뽑아 씀.",null]],3,"채ː택"]},{"0":[["採擇"],[["selection; choice","An act of choosing among many."]],2,"채ː택"]}],"채찍":[{"1":[[],[["말이나 소 따위를 때려 모는 데에 쓰기 위하여, 가는 나무 막대나 댓가지 끝에 노끈이나 가죽 오리 따위를 달아 만든 물건.",null]],2,"채찍"]},{"0":[[],[["whip","A tool made by attaching strings or leather strips to the tip of a stick that is used for whipping and driving horses or cattle."]],0,"채찍"]}],"책징":[{"1":[["責徵"],[["돈, 곡식 따위를 내놓으라고 요구함.",null]],3,"책찡"]},{}],"책롱":[{"1":[["冊籠"],[["책을 넣어 두는 농짝.",null]],3,"챙농"]},{}],"책장":[{"1":[["冊張"],[["책을 이루고 있는 낱낱의 장.",null]],3,"책짱"],"2":[["冊欌"],[["책을 넣어 두는 장.",null]],3,"책짱"]},{"1":[["冊張"],[["page","Each and every sheet in a book."]],0,"책짱"],"2":[["冊欌"],[["bookshelf; bookcase","A piece of furniture for holding books. "]],1,"책짱"]}],"책고":[{"1":[["冊庫"],[["책을 간직하여 두는 창고.",null]],3,"책꼬"]},{}],"채심":[{"1":[["採心"],[["정신을 차리어 가다듬음.",null],["마음속으로 셈하여 생각함. 또는 그런 생각의 내용.",null]],3,"채ː심"]},{}],"채부":[{"1":[["採否"],[["사람을 채용하고 채용하지 아니하는 것.",null],["의견이나 방안을 채택하고 채택하지 아니하는 것.",null]],3,"채ː부"]},{}],"채견":[{"1":[["彩絹"],[["두껍고 무늬가 없는 여러 가지 고운 빛깔의 비단.",null]],3,"채ː견"]},{}],"책실":[{"1":[["冊"],[["책을 매는 데 쓰는 실.",null]],1,"책씰"],"2":[["冊室"],[["조선 시대에, 궁중에서 편찬과 인쇄를 맡아보던 관아. 세종 때에 두었다.","역사"]],3,"책씰"]},{}],"채방":[{"1":[["彩舫"],[["궁중에서, 정재(呈才)를 베풀 때에 선유락에 쓰던 배.","역사"]],3,"채ː방"],"2":[["採訪"],[["모르는 곳을 물어서 찾아감.",null]],3,"채ː방"]},{}],"책방":[{"1":[["冊房"],[["책을 갖추어 놓고 팔거나 사는 가게.",null]],3,"책빵"],"2":[["冊房"],[["조선 시대에, 궁중에서 편찬과 인쇄를 맡아보던 관아. 세종 때에 두었다.","역사"],["고을 원의 비서 일을 맡아보던 사람. 관제(官制)에는 없는데 사사로이 임용하였다.","역사"]],3,"책빵"]},{"0":[["冊房"],[["bookstore","A store that sells books."]],0,"책빵"]}],"채농":[{"1":[["菜農"],[["채소를 가꾸는 농사.","농업"]],3,"채ː농"]},{}],"책루":[{"1":[["柵壘"],[["예전에, 군사들이 주둔하던 곳에 적의 침입을 막고자 세운 울짱이나 흙벽.",null]],3,"챙누"]},{}],"책상다리":[{"1":[["冊床"],[["한쪽 다리를 오그리고 다른 쪽 다리는 그 위에 포개어 얹고 앉은 자세.","없음"],["줄타기 재주의 하나. 줄 위에서 책상다리를 하고 다리를 폈다 오므렸다 한다.","민속"],["부처나 승려의 앉음새의 하나. 두 발을 구부려 각각 양쪽 허벅다리 위에 얹거나 한쪽 발만 얹고 앉는다. 결가부좌, 반가부좌 따위가 있다.","불교"]],1,"책쌍다리"]},{"0":[["冊床다리"],[["cross-legged position","A sitting position in which one leg is placed across the other."]],0,"책쌍다리"]}],"책봉":[{"1":[["冊封"],[["왕세자, 왕세손, 왕후, 비(妃), 빈(嬪), 부마 등을 봉작(封爵)하던 일.","역사"]],3,"책뽕"]},{}],"채저":[{"1":[["菜菹"],[["여름에 푸성귀로 담그는 김치.",null]],3,"채ː저"]},{}],"채사":[{"1":[["使"],[["→ 차사04.","역사"]],1,null]},{}],"채뇨":[{"1":[["採尿"],[["오줌 검사 따위에 쓰기 위하여 오줌을 받음.",null]],3,"채ː뇨"]},{}],"채노":[{"1":[["債奴"],[["빚을 갚는 방편으로 종이 된 노비를 이르던 말.","역사"]],3,"채ː노"]},{}],"채변":[{"1":[[],[["남이 무엇을 줄 때에 사양함.",null],["→ 주변01.",null]],2,"채ː변"],"2":[["採便"],[["기생충 감염 검사나 병리 검사 따위에 쓰기 위하여 똥을 받음. 또는 그 똥.",null]],3,"채ː변"]},{}],"책대":[{"1":[["冊"],[["책을 읽을 때에, 글줄이나 글자를 짚기도 하고 서산을 눌러두기도 하는 가는 막대기.",null]],1,"책때"],"2":[["冊帒"],[["책을 넣는 주머니.",null]],3,"책때"]},{}],"채포":[{"1":[["採捕"],[["해산물 따위를 채취하거나 잡음.",null]],3,"채ː포"],"2":[["菜圃"],[["전문적으로 채소를 심어 가꾸는 규모가 큰 밭.",null]],3,"채ː포"]},{}],"책배":[{"1":[["責拜"],[["임금이 직접 명령을 내리어 벼슬을 맡기던 일.","역사"]],3,"책빼"],"2":[["策配"],[["정치적인 계책으로 지배하는 일.",null]],3,"책빼"]},{}],"책출":[{"1":[["責出"],[["필요한 인원, 마소 따위를 책임지고 차출하던 일.","역사"]],3,"책출"]},{}],"챗돌":[{"1":[[],[["개상 위에 얹어 놓고 태질할 때 쓰는 돌.","농업"]],2,"채똘"]},{}],"책의":[{"1":[["冊衣"],[["책의 맨 앞과 뒤의 겉장.",null],["책의 겉장이 상하지 아니하게 종이, 비닐, 헝겊 따위로 덧씌우는 일. 또는 그런 물건.",null]],3,"채긔"]},{}],"책시":[{"1":[["柵市"],[["‘책문 후시’를 줄여 이르는 말.","역사"]],3,"책씨"],"2":[["策試"],[["정치에 관한 계책을 물어서 답하게 하던 과거(科擧) 과목.","역사"]],3,"책씨"]},{}],"채워진껍질":[{"1":[[],[["파울리(Pauli)의 배타 원리에서 허용하는 최대 수의 전자를 수용한 전자껍질. 전자 밀도는 구대칭이며, 운동량의 합은 0이 된다.","물리"]],2,"채워진껍찔"]},{}],"책전":[{"1":[["冊廛"],[["책을 갖추어 놓고 팔거나 사는 가게.",null]],3,"책쩐"]},{}],"채식주의":[{"1":[["菜食主義"],[["고기류를 피하고 주로 채소, 과일, 해초 따위의 식물성 음식만을 먹는 식생활이 좋다고 생각하는 태도.",null]],3,"채ː식쭈의"]},{"0":[["菜食主義"],[["vegetarianism","An attitude in which one prefers a plant-based diet consisting of vegetables, fruits, seaweed, etc., without meat."]],0,"채ː식쭈의"]}],"책꽂이":[{"1":[["冊"],[["책을 세워서 꽂아 두는 물건이나 장치.",null]],1,"책꼬지"]},{"0":[["冊꽂이"],[["bookshelf","A piece of furniture for holding books."]],0,"책꼬지"]}],"채홍":[{"1":[["彩虹"],[["공중에 떠 있는 물방울이 햇빛을 받아 나타나는, 반원 모양의 일곱 빛깔의 줄. 흔히 비가 그친 뒤 태양의 반대쪽에서 나타난다. 보통 바깥쪽에서부터 빨강, 주황, 노랑, 초록, 파랑, 남색, 보라의 차례이다.",null]],3,"채ː홍"]},{}],"채미충":[{"1":[["蠆尾蟲"],[["전갈과의 하나. 몸의 길이는 3.5~20cm이며 누런색이다. 몸은 짧은 두흉부와 좁고 긴 배로 나뉘는데 꼬리 끝에 독침이 있다. 한국, 중국, 북아메리카, 열대 지방 등지에 분포한다.","동물"]],3,"채ː미충"]},{}],"책세":[{"1":[["冊貰"],[["책을 빌려서 보는 값으로 내는 돈.",null]],3,"책쎄"]},{}],"채승":[{"1":[["綵繩"],[["오색 비단실로 가늘게 꼰 줄.",null]],3,"채ː승"]},{}],"채칼":[{"1":[[],[["야채나 과일 따위를 가늘고 길쭉하게 채 치는 데 쓰는 칼.",null]],2,"채ː칼"]},{"0":[[],[["food slicer","A knife used to slice vegetables or fruit into long, thin slices. "]],0,"채ː칼"]}],"책다듬이벌레":[{"1":[["冊"],[["책다듬이벌렛과의 곤충. 몸의 길이는 1mm 정도이며, 연한 갈색이다. 위아래가 납작하고 날개와 홑눈은 없으며 겹눈은 검은색인데 2~8개의 작은 눈으로 되어 있다. 집 안에서 책, 마른 식료품, 옷, 낟알 따위를 해치는 해충이다.","동물"]],1,"책따드미벌레"]},{}],"채득":[{"1":[["採得"],[["더듬어 살펴서 찾아내거나 알아냄.",null]],3,"채ː득"],"2":[["債得"],[["남에게서 빚을 얻음.",null]],3,"채ː득"]},{}],"채밀":[{"1":[["採蜜"],[["꿀을 뜸.",null]],3,"채ː밀"]},{}],"챌낚":[{"1":[[],[["낚싯대를 쓰지 아니하고 물고기가 물리면 낚싯줄을 채서 끌어내는 도구.",null]],2,"챌락"]},{}],"챔질":[{"1":[[],[["낚시에서, 고기가 미끼를 건드려서 찌가 움직일 때 낚싯대를 살짝 들어 올리는 일.","체육"]],2,"챔질"]},{}],"채여":[{"1":[["彩轝","彩輿"],[["왕실 의식 때에 귀중품을 실어 옮기던 기구. 교자(轎子)와 비슷한데, 꽃무늬가 채색되어 있고, 채가 달려 있어 앞뒤에서 두 사람이 메게 되어 있다.","역사"]],3,"채ː여"]},{}],"채집":[{"1":[[],[["비단에 수를 놓아 곱게 꾸민 바늘 주머니.",null]],2,"채집"],"2":[["採集"],[["널리 찾아서 얻거나 캐거나 잡아 모으는 일.",null]],3,"채ː집"]},{"0":[["採集"],[["collection","An act of gathering by searching widely and then assembling, digging out, or catching. "]],0,"채ː집"]}],"채빙":[{"1":[["採氷"],[["얼어붙은 강바닥, 빙벽 따위에서 얼음을 자르거나 쳐서 필요한 만큼 얻어 냄.","없음"]],3,"채ː빙"]},{}],"채석장":[{"1":[["採石場"],[["석재(石材)로 쓸 돌을 캐거나 떠 내는 곳.",null]],3,"채ː석짱"]},{"0":[["採石場"],[["quarry","A place where stones are dug or cut for civil engineering or construction."]],0,"채ː석짱"]}],"채록":[{"1":[["採錄"],[["필요한 자료를 찾아 모아서 적거나 녹음함. 또는 그런 기록이나 녹음.",null]],3,"채ː록"]},{"0":[["採錄"],[["record","An act of documenting or recording necessary data for something, or such a document or recording."]],0,"채ː록"]}],"채기":[{"1":[[],[["낚시에서, 물고기가 입질할 때 물고기를 낚아채는 일.","체육"]],2,"채기"],"2":[["彩旗"],[["아름다운 빛깔을 물들인 기.",null]],3,"채ː기"],"3":[["彩器"],[["그림을 그릴 때, 여러 가지 빛깔의 물감을 풀어서 담아 쓰는 그릇.",null]],3,"채ː기"],"4":[["綵綺"],[["고운 빛깔의 무늬가 있는 비단.",null]],3,"채ː기"]},{}],"채용":[{"1":[["採用"],[["사람을 골라서 씀.",null],["어떤 의견, 방안 등을 고르거나 받아들여서 씀.",null]],3,"채ː용"],"2":[["債用"],[["돈이나 물건 따위를 빌려서 씀.",null]],3,"채ː용"]},{"0":[["採用"],[["recruitment; hire","An act of hiring an employee."],["adoption; application","An act of selecting or accepting an opinion, way, etc., and applying it."]],3,"채ː용"]}],"채산":[{"1":[["採山"],[["산에서 나물을 캠.",null]],3,"채ː산"],"2":[["採算"],[["수입과 지출을 맞추어 계산함. 또는 그 계산 내용.","경제"],["원가에 비용, 이윤 따위를 더하여 파는 값을 정함. 또는 그렇게 이익이 있도록 맞춘 계산 내용.","경영"]],3,"채ː산"]},{}],"책동":[{"1":[["策動"],[["좋지 아니한 일을 몰래 꾸미어 시행함.",null],["남을 부추기어 일정한 방향으로 행동하게 함.",null]],3,"책똥"]},{"0":[["策動"],[["scheme; conspiracy","An act of plotting a devious plan and actually carrying it out."],["maneuver","An act of inciting others to do as one wishes."]],0,"책똥"]}],"책려":[{"1":[["策勵"],[["채찍질을 하듯 격려함.",null]],3,"챙녀"]},{}],"책형":[{"1":[["磔刑"],[["기둥에 묶어 세우고 창으로 찔러 죽이던 형벌.","역사"]],3,"채켱"]},{}],"채벽":[{"1":[["採壁"],[["채석장에서, 돌을 뜨는 암벽의 단면.","광업"],["갱도의 막다른 곳.","광업"]],3,"채ː벽"]},{}],"채널":[{"1":[[],[["어떠한 일을 이루는 방법이나 정보가 전달되는 경로.",null],["텔레비전ㆍ라디오ㆍ무선 통신 따위에서, 주파수대에 따라 각 방송국에 배정된, 전파의 전송(傳送) 통로.","정보·통신"],["중앙 처리 장치 대신에 입출력 동작을 수행하는 장치.","정보·통신"]],4,null]},{"0":[["channel"],[["channel","A course through which information is transmitted or a method of achieving something."],["channel","A transmission path for radio waves distributed to a television or radio broadcaster, radio communications service, etc., according to the frequency level."]],2,null]}],"채선":[{"1":[["彩扇"],[["채색한 부채.",null]],3,"채ː선"],"2":[["彩船"],[["궁중에서, 정재(呈才)를 베풀 때에 선유락에 쓰던 배.","역사"]],3,"채ː선"]},{}],"채례":[{"1":[["采禮"],[["혼인할 때에, 사주단자의 교환이 끝난 후 정혼이 이루어진 증거로 신랑집에서 신붓집으로 예물을 보냄. 또는 그 예물. 보통 밤에 푸른 비단과 붉은 비단을 혼서와 함께 함에 넣어 신붓집으로 보낸다.","민속"]],3,"채ː례"]},{}],"채과":[{"1":[["菜果"],[["채소와 과일을 아울러 이르는 말.",null]],3,"채ː과"]},{}],"책응":[{"1":[["責應"],[["책임지고 물건을 내어줌.","없음"]],3,"채긍"],"2":[["策應"],[["계책을 통하여 서로 응하고 도움.",null]],3,"채긍"]},{}],"채설기":[{"1":[["採雪器"],[["눈의 표본을 채취하는 데 쓰는 속이 빈 관(管).",null]],3,"채ː설기"]},{}],"책재원수":[{"1":[["責在元帥"],[["가장 높은 지위에 있는 사람에게 책임이 있음.",null]],3,"책째원수"]},{}],"채리엇":[{"1":[[],[["고대 이집트, 그리스, 로마 등지에서 쓰던 두 바퀴 전차. 두 마리의 말이 끌고 한 사람이 타는 것으로, 사냥할 때에도 썼다.","역사"]],4,null]},{}],"챗열":[{"1":[[],[["채찍 따위의 끝에 달리어 늘어진 끈.",null]],2,"챈녈"]},{}],"채병":[{"1":[["彩屛"],[["채색한 그림을 그려 넣은 병풍.",null]],3,"채ː병"]},{}],"채량미":[{"1":[["債糧米"],[["양식으로 쓰려고 꾼 쌀.",null]],3,"채ː량미"]},{}],"채죽뒤":[{"1":[[],[["활을 당길 때에, 팔꿈치에 힘을 가하지 아니하고 손회목으로만 당기는 좋지 아니한 활쏘기 자세.","체육"]],2,"채죽뛰"]},{}],"채고추나물":[{"1":[[],[["물레나물과의 여러해살이풀. 높이는 30~80cm이며, 잎은 마주나고 긴 타원형이다. 고추나물과 비슷하나 줄기에 검은 점이 있고 꽃이 조금 크다. 7~8월에 노란색 꽃이 줄기 끝이나 가지 끝에 취산(聚繖) 화서로 피고 열매는 달걀 모양의 삭과(蒴果)이며 어린잎은 식용한다. 산이나 들에서 자라는데 한국, 중국, 몽골 등지에 분포한다.","식물"]],2,"채ː고추나물"]},{}],"책상":[{"1":[["冊床"],[["앉아서 책을 읽거나 글을 쓰거나 사무를 보거나 할 때에 앞에 놓고 쓰는 상.",null]],3,"책쌍"],"2":[["柵狀"],[["울타리같이 생긴 모양.",null]],3,"책쌍"]},{"0":[["冊床"],[["desk","A table at which one reads a book, writes, or handles office work. "]],1,"책쌍"]}],"채신머리":[{"1":[[],[["‘처신’을 속되게 이르는 말.",null]],2,"채ː신머리"]},{"0":[[],[["conduct; demeanor","(slang) One's behavior or attitude necessary to lead a life in this world."]],0,"채ː신머리"]}],"책임감":[{"1":[["責任感"],[["맡아서 해야 할 임무나 의무를 중히 여기는 마음.",null]],3,"채김감"]},{"0":[["責任感"],[["sense of responsibility","A sense that one considers one's task or duty important."]],2,"채김감"]}],"책립":[{"1":[["冊立"],[["황태자나 황후를 황제의 명령으로 봉하여 세우던 일.","역사"]],3,"챙닙"],"2":[["責立"],[["필요한 인원, 마소 따위를 책임지고 차출하던 일.","역사"]],3,"챙닙"]},{}],"채란":[{"1":[["採卵"],[["닭이나 물고기 따위의 알을 인위적인 방법으로 낳게 하여 받아 거둠.",null]],3,"채ː란"]},{}],"채붕":[{"1":[["綵棚"],[["나무로 단을 만들고 오색 비단 장막을 늘어뜨린 장식 무대. 신라 진흥왕 때 시작한 팔관회에서부터 설치된 기록이 있다.","연기"],["임금이 행차하거나 중국의 칙사가 지나갈 때, 이를 환영하는 뜻으로 여러 빛깔이 있는 실, 종이, 헝겊 따위를 문이나 지붕, 다리, 길에 내다 걸어 장식하던 일.","역사"]],3,"채ː붕"]},{}],"채신":[{"1":[[],[["‘처신’을 낮잡아 이르는 말.",null]],2,"채ː신"]},{"0":[[],[["conduct; demeanor","(disparaging) One's behavior or attitude necessary to lead a life in this world."]],0,"채ː신"]}],"채궁자리":[{"1":[[],[["판소리 장단에서, 채로 치는 북의 오른쪽 가죽 자리. 악절의 시작에 이 자리를 크게 친다.","음악"]],2,"채궁자리"]},{}],"채점":[{"1":[["採點"],[["시험 답안의 맞고 틀림을 살피어 점수를 매김.",null],["얻은 점수에 따라 성적의 좋고 나쁨을 결정함.",null]],3,"채ː쩜"]},{"0":[["採點"],[["grading; marking","An act of evaluating a test or game. "]],0,"채ː쩜"]}],"챔피언":[{"1":[[],[["운동 종목 따위에서, 선수권을 보유하고 있는 사람.","체육"],["기술 따위에서, 실력이 가장 뛰어난 사람.",null]],4,null]},{"0":[["champion"],[["winner; champion","A person who wins in a sports game and takes the position or qualification of first place."],["champion","A person who is superior in skills, etc."]],2,null]}],"채도":[{"1":[["彩度"],[["색의 선명한 정도. 색의 삼요소의 하나로, 유채색에만 있으며, 회색을 섞을수록 낮아진다.","예체능 일반"]],3,"채ː도"],"2":[["彩陶"],[["중국의 허난성(河南省) 양사오(仰韶)에서 출토된 칠무늬 토기. 적색, 흑색 따위로 채색되었으며 짐승 무늬, 기하학적 무늬 따위가 새겨져 있다.","역사"]],3,"채ː도"],"3":[["菜刀"],[["야채나 과일 따위를 가늘고 길쭉하게 채 치는 데 쓰는 칼.",null]],3,"채ː도"]},{"0":[["彩度"],[["saturation; chroma; vividness; intensity","The degree of the brightness and vividness of colors."]],0,"채ː도"]}],"채녀":[{"1":[["采女"],[["중국 한(漢)나라 때에 있었던 궁녀의 계급. 또는 그 계급의 궁녀.","역사"]],3,"채ː녀"]},{}],"채종":[{"1":[["採種"],[["좋은 씨앗을 골라서 받음.",null]],3,"채ː종"],"2":[["菜種"],[["채소의 씨앗.",null]],3,"채ː종"]},{}],"채장":[{"1":[[],[["조선 시대에, 보부상에게 발급하던 신분증명서.","역사"]],2,"채장"],"2":[["菜腸"],[["늘 채식을 하는 습관에 길든 위와 창자.",null]],3,"채ː장"],"3":[["債帳"],[["남에게 빌린 돈의 금액을 적는 장부.",null]],3,"채ː장"],"4":[["綵帳"],[["여러 가지 빛깔의 비단 따위로 화려하게 꾸민 휘장이나 포장.",null]],3,"채ː장"]},{}],"채자":[{"1":[["採字"],[["활판(活版) 인쇄에서 원고 내용대로 활자를 골라 뽑는 일.","매체"]],3,"채ː자"]},{}],"채결":[{"1":[["採決"],[["의장이 의안(議案)의 채택 가부를 물어 결정함.",null]],3,"채ː결"]},{}],"채찍질":[{"1":[[],[["채찍으로 치는 일.",null],["몹시 재촉하면서 다그치거나 일깨워 힘차게 북돋아 주는 일을 비유적으로 이르는 말.",null]],2,"채찍찔"]},{"0":[[],[["whipping; lashing","An act of beating a person or animal with a whip."],["whipping","(figurative) An act of rushing or encouraging to raise one's spirits by pressing."]],0,"채찍찔"]}],"책력":[{"1":[["冊曆"],[["일 년 동안의 월일, 해와 달의 운행, 월식과 일식, 절기, 특별한 기상 변동 따위를 날의 순서에 따라 적은 책.",null]],3,"챙녁"]},{}],"채묘":[{"1":[["採苗"],[["모를 내기 위하여 모판에서 모를 뽑음. 또는 그런 일.","농업"]],3,"채ː묘"]},{}],"채지":[{"1":[["采地"],[["고대 중국에서, 왕족, 공신, 대신들에게 공로에 대한 특별 보상으로 주는 영지(領地). 그 지역 조세를 받아 먹게 하였고, 봉작과 함께 대대로 상속되었다.","역사"]],3,"채ː지"],"2":[["彩地"],[["빛깔이 칠하여진 바탕.",null]],3,"채ː지"],"3":[["菜芝"],[["백합과의 여러해살이풀. 꽃줄기의 높이는 30~60cm이며, 잎은 비늘줄기에서 뭉쳐나고 속이 비어 있다. 가을에 자주색 꽃이 산형(繖形) 화서로 피고 열매를 맺지 못한다. 잎은 절여서 먹으며, 중국 남부가 원산지이다.","식물"]],3,"채ː지"]},{}],"채탄":[{"1":[["採炭"],[["석탄을 캐내는 일.","광업"]],3,"채ː탄"]},{}],"채진목":[{"1":[["菜振木"],[["장미과의 낙엽 활엽 관목 또는 소교목. 높이는 5미터 정도이며, 잎은 어긋나고 달걀 모양인데 가에 톱니가 있다. 4~5월에 흰 꽃이 가지 끝에 총상(總狀) 화서로 피고 열매는 이과(梨果)로 9월에 붉게 익는다. 목재는 세공재(細工材)로 쓰고 열매는 식용한다. 산 중턱에서 자라는데 한국의 제주도, 일본, 중국 등지에 분포한다.","식물"]],3,"채ː진목"]},{}],"채읍":[{"1":[["采邑"],[["고대 중국에서, 왕족, 공신, 대신들에게 공로에 대한 특별 보상으로 주는 영지(領地). 그 지역 조세를 받아 먹게 하였고, 봉작과 함께 대대로 상속되었다.","역사"]],3,"채ː읍"]},{}],"채팅":[{"1":[[],[["전자 게시판이나 통신망에서, 여러 사용자가 다양한 주제를 가지고 실시간으로 모니터 화면을 통하여 대화를 나누는 일.","매체"]],4,null]},{"0":[["chatting"],[["online chat","A type of communication over the Internet in which several users can have a conversation in real-time through their monitors."]],3,null]}],"책인즉명":[{"1":[["責人則明"],[["남을 탓하는 데 밝다는 뜻으로, 제 잘못은 생각하지 않고 남의 잘못만 나무람을 이르는 말.",null]],3,"채긴증명"]},{}],"책면":[{"1":[["策勉"],[["채찍질을 하듯 격려함.",null]],3,"챙면"]},{}],"채소":[{"1":[["菜蔬"],[["밭에서 기르는 농작물. 주로 그 잎이나 줄기, 열매 따위를 식용한다. 보리나 밀 따위의 곡류는 제외한다.",null]],3,"채ː소"]},{"0":[["菜蔬"],[["vegetable","A plant grown in a field, of which the leaves, stems, or fruits are edible."]],1,"채ː소"]}],"채상":[{"1":[["象"],[["풍물놀이에서, 끝에 헝겊으로 만든 긴 채를 단 상모.","민속"]],1,"채상"],"2":[["彩裳"],[["물감을 들인 치마.",null]],3,"채ː상"],"3":[["彩箱"],[["대나무를 가늘게 쪼개어 채색한 무늬를 놓아 만든 상자.",null]],3,"채ː상"],"4":[["採桑"],[["뽕을 땀.",null]],3,"채ː상"]},{}],"책명":[{"1":[["冊名"],[["책의 이름.",null]],3,"챙명"],"2":[["冊命"],[["왕세자, 왕세손, 비빈(妃嬪) 들을 책봉(冊封)하던 임금의 명령.","역사"]],3,"챙명"],"3":[["策命"],[["임금이 신하에게 내려서 명령하던 글발.","역사"]],3,"챙명"]},{}],"채문":[{"1":[["彩紋"],[["아름답게 채색한 무늬.",null],["물결 모양, 호선(弧線), 원형 따위를 써서 정밀하게 그린 기하학적 무늬. 흑채문과 백채문이 있으며, 지폐나 증권 따위의 위조를 막기 위하여 그 도안의 바탕 그림으로 쓰기도 한다.",null]],3,"채ː문"],"2":[["採問"],[["알려지지 않은 사실이나 소식 따위를 알아내기 위하여 더듬어 찾아 물음.",null]],3,"채ː문"]},{}],"챗배":[{"1":[[],[["채그물로 물고기를 잡는 배. 주로 남해, 제주도 근해에서 멸치를 잡을 때 쓴다.","수산업"]],2,"채빼"]},{}],"책훈":[{"1":[["策勳"],[["국가나 군주 등을 위하여 공훈을 세운 사람의 이름과 공훈을 문서에 기록함. 또는 그 공훈을 찬양하여 상을 줌.",null]],3,"채쿤"]},{}],"채의":[{"1":[["彩衣"],[["여러 가지 빛깔과 무늬가 있는 옷.",null]],3,"채ː의"]},{}],"채루":[{"1":[["彩樓"],[["아름답게 칠한 누각.","건설"]],3,"채ː루"]},{}],"채니기":[{"1":[["採泥器"],[["바다, 하천, 호수 따위의 바닥에서 진흙, 모래, 그 밖의 침전물 따위를 긁어내는 장치. 지하자원의 조사와 퇴적의 역사적 연구와 물 밑의 지질 연구 따위에 쓰며, 드레저식ㆍ코러식ㆍ진공식ㆍ주상식 따위가 있다.","해양"]],3,"채ː니기"]},{}],"채풍":[{"1":[["采風"],[["드러나 보이는 사람의 겉모양.",null]],3,"채ː풍"]},{}],"채":[{"1":[[],[["발구, 달구지, 수레 따위의 앞쪽 양옆에 댄 긴 나무.",null],["가마, 들것, 목도 따위의 앞뒤로 양옆에 대서 메거나 들게 되어 있는 긴 나무 막대기.",null]],2,"채"],"2":[[],[["머리카락이나 수염 따위가 길게 늘어진 것.",null]],2,"채"],"3":[[],[["염색할 때에, 물감이 고르게 들지 아니하여서 줄이 죽죽 쳐진 얼룩.",null]],2,"채"],"4":[[],[["껍질을 벗긴 싸릿개비나 가는 나무오리. 바구니, 광주리 따위를 만드는 데 쓴다.",null]],2,"채"],"5":[[],[["팽이, 공 따위의 대상을 치는 데에 쓰는 기구.",null],["벌로 사람을 때리는 데에 쓰는 나뭇가지.",null],["말이나 소 따위를 때려 모는 데에 쓰기 위하여, 가는 나무 막대나 댓가지 끝에 노끈이나 가죽 오리 따위를 달아 만든 물건.",null],["북, 장구, 꽹과리, 징 따위의 타악기를 치거나 현악기를 타서 소리를 내게 하는 도구.","음악"]],2,"채"],"6":[[],[["야채나 과일 따위를 가늘고 길쭉하게 잘게 써는 일. 또는 그 야채나 과일.",null]],2,"채ː"],"7":[[],[["풍물놀이의 기본이 되는 악장. 세 가락으로 이루어진다. 현재 열두 개가 전한다.","예체능 일반"]],2,"채"],"11":[[],[["은어로, ‘떡01’을 이르는 말.",null]],2,"채"],"12":[["采"],[["우리나라 성(姓)의 하나. 주요 본관은 여산(礪山)이 현존한다.",null]],3,"채"],"13":[["菜"],[["채소나 과류(瓜類) 따위를 재료로 간과 양념을 쳐서 만든 반찬.",null]],3,"채ː"],"14":[["菜"],[["우리나라 성(姓)의 하나. 본관은 진주(晉州) 하나뿐이다.",null]],3,"채ː"],"15":[["蔡"],[["우리나라 성(姓)의 하나. 본관은 평강(平康), 인천(仁川), 경주(慶州), 음성(陰城), 광주(光州) 등이 현존한다.",null]],3,"채ː"],"16":[["蔡"],[["중국 주나라 때에, 무왕의 아우 숙도(叔度)를 봉하여 준 나라. 수도는 지금의 허난성(河南省) 상차이현(上蔡縣)의 남쪽 지방이며, 기원전 445년에 초나라에 망하였다.","역사"]],3,"채ː"]},{"1":[[],[["chae","stick; racket: An implement used to spin a top or hit a ball, etc., with."],["stick","A thin rod used to spank people for punishment."],["whip","A tool made by attaching strings or leather strips to the tip of a stick that is used for whipping and driving horses or cattle."],["chae","stick: An implement used to play percussion or string instruments such as the buk, a barrel drum, janggu, an hourglass-shaped drum, kkwaenggwari, a small gong, jing, a larger gong, etc."]],0,"채"],"2":[[],[["julienne; allumette","A way of cutting vegetables, fruits, etc., into long thin strips, or such a vegetable or fruit."]],0,"채ː"]}],"책선":[{"1":[["蚱蟬"],[["매밋과의 곤충. 몸의 길이는 4.5cm, 날개의 길이는 6.5cm 정도로 우리나라 매미 가운데 가장 크다. 검은색에 날개는 투명하고 다리와 배에 황금색의 잔털이 나 있다. 아침부터 아주 크고 강한 소리로 운다. 한국, 일본, 중국 등지에 분포한다.","동물"]],3,"책썬"],"2":[["責善"],[["벗 사이에 착하고 좋은 일을 하도록 서로 권함.",null]],3,"책썬"]},{}],"채색":[{"1":[["采色"],[["풍채와 안색을 아울러 이르는 말.",null]],3,"채ː색"],"2":[["彩色"],[["여러 가지의 고운 빛깔.",null],["그림 따위에 색을 칠함.",null],["채색하는 데에 쓰는 물감, 단청 따위의 재료.",null]],3,"채ː색"],"3":[["菜色"],[["푸성귀의 빛깔.",null],["병들거나 굶주려서 핏기가 없이 누르스름한 얼굴 빛깔.",null]],3,"채ː색"]},{"0":[["彩色"],[["variegated colors","Different fair colors."],["coloring","An act of applying color to a painting, etc."],["color paint","A paint used to apply color."]],0,"채ː색 "]}],"채습":[{"1":[["採拾"],[["따거나 주워서 모아 가짐.",null],["섶나무를 베고 나무 열매를 주워 모은다는 뜻으로, 가난한 생활을 비유적으로 이르는 말.",null]],3,"채ː습"]},{}],"채약":[{"1":[["採藥"],[["약초나 약재를 캐거나 뜯어서 거둠.",null]],3,"채ː약"]},{}],"책거리":[{"1":[["冊"],[["책이나 벼루, 먹, 붓, 붓꽂이, 두루마리꽂이 따위의 문방구류를 그린 그림.",null]],1,"책꺼리"],"2":[["冊"],[["글방 따위에서 학생이 책 한 권을 다 읽어 떼거나 다 베껴 쓰고 난 뒤에 선생과 동료들에게 한턱내는 일.",null]],1,"책꺼리"]},{"0":[["冊거리"],[["celebration of finishing a book","An act of celebrating the completion of studying a book from beginning to end."]],0,"책꺼리"]}],"채일":[{"1":[["日"],[["→ 차일02.",null]],1,null]},{}],"채삼":[{"1":[["採蔘"],[["인삼을 캠.",null]],3,"채ː삼"]},{}],"채보":[{"1":[["砦堡"],[["적을 막기 위하여 쌓은 작은 성.",null]],3,"채보"],"2":[["採譜"],[["곡조를 듣고 그것을 악보로 만듦.","음악"]],3,"채ː보"]},{}],"책자":[{"1":[["冊子"],[["일정한 목적, 내용, 체재에 맞추어 사상, 감정, 지식 따위를 글이나 그림으로 표현하여 적거나 인쇄하여 묶어 놓은 것.",null]],3,"책짜"]},{"0":[["冊子"],[["books; publications","Writings, pictures, etc., that are printed and bound."]],3,"책짜"]}],"책점":[{"1":[["冊店"],[["책을 갖추어 놓고 팔거나 사는 가게.",null]],3,"책쩜"]},{}],"책살":[{"1":[["磔殺"],[["기둥에 묶어 세우고 창으로 찔러 죽임.",null]],3,"책쌀"]},{}],"책권":[{"1":[["冊卷"],[["책의 권이라는 뜻으로, 구체적인 책 하나하나를 이르는 말.",null],["어느 정도 되는 양의 책.",null]],3,"책꿘"]},{}],"채두":[{"1":[["菜豆"],[["→ 강낭콩「1」.","식물"]],3,null],"2":[["菜頭"],[["절에서, 부식물을 만들거나 그 재료인 야채를 관리하는 일. 또는 그런 사람.","불교"]],3,"채ː두"]},{}],"책안":[{"1":[["冊案"],[["책봉문을 놓던 상(床).","역사"]],3,"채간"]},{}],"채금":[{"1":[["彩衾"],[["빛깔이 곱고 아름다운 이부자리.",null]],3,"채ː금"],"2":[["採金"],[["금을 캐는 일.","광업"]],3,"채ː금"],"3":[["債金"],[["돈을 꾸어 옴. 또는 그 돈.",null]],3,"채ː금"]},{}],"책벌레":[{"1":[["冊"],[["지나치게 책을 읽거나 공부하는 데만 열중하는 사람을 놀림조로 이르는 말.",null]],1,"책뻘레"]},{"0":[["冊벌레"],[["bookworm","(teasing) A person who reads or studies excessively. "]],0,"책뻘레"]}],"채시":[{"1":[["采詩"],[["중국 주(周)나라 때에, 민간에서 유행하는 노래와 시를 모으던 일. 이로써 풍속을 고찰하여 정치의 참고 자료로 이용하였다.","문학"]],3,"채ː시"]},{}],"채무자":[{"1":[["債務者"],[["특정인에게 일정한 빚을 갚아야 할 의무를 가진 사람.","법률"]],3,"채ː무자"]},{"0":[["債務者"],[["debtor","A person who has the obligation to pay a debt to someone."]],0,"채ː무자"]}],"책정":[{"1":[["策定"],[["계획이나 방책을 세워 결정함.",null]],3,"책쩡"]},{"0":[["策定"],[["arrangement","An act of setting up a plan or method to decide."]],0,"책쩡"]}],"채무":[{"1":[["債務"],[["재산권의 하나. 특정인이 다른 특정인에게 어떤 행위를 하여야 할 의무를 이른다.","법률"]],3,"채ː무"]},{"0":[["債務"],[["debt; liabilities","An obligation to give something to or do something for another person."]],0,"채ː무"]}],"채납":[{"1":[["採納"],[["의견을 받아들임.",null],["사람을 골라서 들임.",null]],3,"채ː납"]},{}],"채복":[{"1":[["彩服"],[["색깔이 고운 옷.",null]],3,"채ː복"]},{}],"채희":[{"1":[["采戲"],[["주사위를 던지며 하는 놀이.",null]],3,"채ː히"]},{}],"책맹":[{"1":[["舴艋"],[["거룻배의 하나.",null]],3,"챙맹"],"2":[["蚱蜢"],[["메뚜깃과의 곤충을 통틀어 이르는 말. 겹눈과 세 개의 홑눈이 있고 뒷다리가 발달하여 잘 뛴다. 불완전 변태를 하며 알로 겨울을 난다.","동물"]],3,"챙맹"]},{}],"채담":[{"1":[["彩毯"],[["여러 가지 빛깔의 털로 무늬를 놓아 짠 긴 네모꼴의 담요.",null]],3,"채ː담"]},{}]}