{"푼수":[{"1":[[],[["얼마에 상당한 정도.",null],["상태나 형편.",null],["생각이 모자라고 어리석은 사람을 놀림조로 이르는 말.",null]],2,"푼ː수"]},{"0":[[],[["situation; state","One's situation or state."],["idiot","(teasing) A slow-witted, stupid person."]],0,"푼ː수"]}],"푼칭":[{"1":[["秤"],[["→ 분칭.",null]],1,null]},{}],"푼푼":[{"1":[[],[["한 푼 한 푼의 돈.",null]],2,"푼ː푼"]},{}],"푼타아레나스":[{"1":[[],[["남아메리카 칠레 남부에 있는 도시. 양털, 양고기 따위를 수출한다. 마가야네스주의 주도(州都)이다.","지명"]],4,null]},{}],"푼겐스소나무":[{"1":[[],[["소나뭇과의 상록 침엽 교목. 잎은 두 개씩 뭉쳐난다. 암수한그루로 5월에 자색의 긴 웅화수는 원뿔형으로, 자화수는 달걀 모양으로 피고 열매는 구과(毬果)로 다음 해 10월에 익는다. 목재는 땔감으로 쓰고 정원수로 재배한다. 북아메리카가 원산지로 비옥한 땅에서 자라는데 우리나라 각지에 분포한다.","식물"]],1,null]},{}],"푼샬":[{"1":[[],[["대서양 동부, 마데이라섬 동쪽 기슭에 있는 항구 도시. 포르투갈령으로 경치가 아름답고 기후가 온난하여 관광지ㆍ휴양지로 알려졌으며, 포도주 생산으로도 유명하다.","지명"]],4,null]},{}],"푼사":[{"2":[["絲"],[["고치를 켠 그대로 꼬지 아니한 명주실. 여러 색을 물들여 수를 놓는 데 쓴다.",null]],1,"푼사"]},{}],"푼침":[{"1":[["針"],[["→ 분침01.",null]],1,null]},{}],"푼거리질":[{"1":[[],[["몇 푼어치씩 땔나무나 물건 따위를 사서 쓰는 일.",null]],2,"푼ː거리질"]},{}],"푼수데기":[{"1":[[],[["생각이 모자라고 어리석은 사람을 낮잡아 이르는 말.",null]],2,"푼ː수떼기"]},{}],"푼전입미":[{"1":[["錢粒米"],[["‘분전입미’의 변한말.",null]],1,"푼ː전님미"]},{}],"푼내기흥정":[{"1":[[],[["푼돈으로 셈하는 잔흥정.",null]],2,"푼ː내기흥정"]},{}],"푼거리나무":[{"1":[[],[["몇 푼어치씩 팔고 사는 땔나무.",null]],2,"푼ː거리나무"]},{}],"푼돈":[{"1":[[],[["많지 아니한 몇 푼의 돈.",null],["적은 액수로 나뉜 돈.",null]],2,"푼ː똔"]},{"0":[[],[["small change","An amount of money that is not big."]],0,"푼ː똔"]}],"푼전승량":[{"1":[["錢升糧"],[["‘분전승량’의 변한말.",null]],1,"푼ː전승냥"]},{}],"푼주":[{"1":[[],[["아가리는 넓고 밑은 좁은 너부죽한 사기그릇.",null]],2,"푼ː주"]},{}],"푼자":[{"1":[[],[["→ 푼주.",null]],2,null]},{}],"푼리":[{"1":[["厘"],[["‘분리02’의 변한말.",null]],1,"풀ː리"]},{}],"푼지나무":[{"1":[[],[["노박덩굴과의 낙엽 활엽 덩굴성 나무. 길이는 5미터 정도이며, 잎은 어긋나고 넓은 타원형 또는 달걀 모양이다. 6월에 녹색을 띤 노란색 꽃이 잎겨드랑이에 한두 개 피고 열매는 삭과(蒴果)로 10월에 누렇게 익는다. 어린잎은 식용하고 산기슭이나 개울가의 숲속에서 자라는데 한국, 일본, 중국, 아무르 등지에 분포한다.","식물"]],2,"푼지나무"]},{}]}