{
    "id": 937315,
    "authors": [
        {
            "id": 13791036,
            "name": "CarlosAMolina",
            "url": "https://addons.mozilla.org/en-US/firefox/user/13791036/",
            "username": "CarlosAMolina"
        }
    ],
    "average_daily_users": 160,
    "categories": [
        "web-development",
        "appearance",
        "tabs"
    ],
    "contributions_url": "",
    "created": "2018-02-16T21:28:02Z",
    "current_version": {
        "id": 5805273,
        "compatibility": {
            "firefox": {
                "min": "58.0",
                "max": "*"
            },
            "android": {
                "min": "120.0",
                "max": "*"
            }
        },
        "edit_url": "https://addons.mozilla.org/en-US/developers/addon/check-iframe/versions/5805273",
        "file": {
            "id": 4349563,
            "created": "2024-09-08T19:27:27Z",
            "hash": "sha256:2cfbb60e04c2889d1b7ee0fe21822c4a891e9552c53172ebedd3c3c3ca9cb154",
            "is_mozilla_signed_extension": false,
            "size": 102439,
            "status": "public",
            "url": "https://addons.mozilla.org/firefox/downloads/file/4349563/check_iframe-1.6.0.xpi",
            "permissions": [
                "activeTab",
                "storage",
                "tabs",
                "https://*/*",
                "http://*/*",
                "file:///*"
            ],
            "optional_permissions": [],
            "host_permissions": []
        },
        "is_strict_compatibility_enabled": false,
        "license": {
            "id": 3338,
            "is_custom": false,
            "name": {
                "en-US": "Mozilla Public License 2.0"
            },
            "slug": "MPL-2.0",
            "url": "https://www.mozilla.org/MPL/2.0/"
        },
        "release_notes": {
            "en-US": "Add automatic highlighting (i)frames.\nImprove front."
        },
        "reviewed": "2024-09-08T19:30:28Z",
        "version": "1.6.0"
    },
    "default_locale": "en-US",
    "description": {
        "en-US": "<b>Introduction</b>\n\nThis is a Firefox add-on to work with iframe and frame tags:\n\n<ul>  <li>Indicate if the current web page uses iframe and frame tags by changing the colour of the add-on icon.</li>  <li>Scroll the window to the elements with tags and highlight them with a red border.</li>  <li>Redirection. A list of sites where the add-on will apply a redirection automatically to the first iframe/frame source can be configured.</li></ul>\nThe meaning of the icon's colours is: \n\n<ul>  <li>Gray icon: the website cannot be checked.</li>  <li>Green icon: no tag iframe or frame detected.</li>  <li>Orange icon: tag detected.</li>  <li>Purple icon: tag detected and at least one source matches with any term in the configured user's list of special sources to notify.</li></ul>\n<b>Documentation</b>\n\nPlease, read the docs to know how to configure the add-on, work with it and more information:\n\n<a href=\"https://prod.outgoing.prod.webservices.mozgcp.net/v1/54e0ea428e13dcd6a52eceac0b219ffd2da359450ee1cd326b299daa8c4c344b/https%3A//cmoli.es/projects/check-iframe/introduction.html\" rel=\"nofollow\">https://cmoli.es/projects/check-iframe/introduction.html</a>\n\n<b>GitHub</b>\n\n<a href=\"https://prod.outgoing.prod.webservices.mozgcp.net/v1/50fe0a6f6efe17b7f19f5a07d5dcf235f76ed5e6791c5722c1ada9cb099975dc/https%3A//github.com/carlosamolina/checkiframe\" rel=\"nofollow\">https://github.com/carlosamolina/checkiframe</a>"
    },
    "developer_comments": null,
    "edit_url": "https://addons.mozilla.org/en-US/developers/addon/check-iframe/edit",
    "guid": "{117d8485-1088-4ce1-9050-5e9a05e6a8ee}",
    "has_eula": false,
    "has_privacy_policy": false,
    "homepage": {
        "url": {
            "en-US": "https://github.com/CarlosAMolina/checkIframe"
        },
        "outgoing": {
            "en-US": "https://prod.outgoing.prod.webservices.mozgcp.net/v1/71afa49e035cbcbe6d517f01c43e9f221dd7bb62d838fdc674aafcd06c7d7935/https%3A//github.com/CarlosAMolina/checkIframe"
        }
    },
    "icon_url": "https://addons.mozilla.org/user-media/addon_icons/937/937315-64.png?modified=a8e6ac19",
    "icons": {
        "32": "https://addons.mozilla.org/user-media/addon_icons/937/937315-32.png?modified=a8e6ac19",
        "64": "https://addons.mozilla.org/user-media/addon_icons/937/937315-64.png?modified=a8e6ac19",
        "128": "https://addons.mozilla.org/user-media/addon_icons/937/937315-128.png?modified=a8e6ac19"
    },
    "is_disabled": false,
    "is_experimental": false,
    "last_updated": "2024-09-08T19:30:28Z",
    "name": {
        "en-US": "Check iframe"
    },
    "previews": [
        {
            "id": 304997,
            "caption": {
                "en-US": "Website with (i)frames."
            },
            "image_size": [
                1174,
                600
            ],
            "image_url": "https://addons.mozilla.org/user-media/previews/full/304/304997.png?modified=1725825325",
            "position": 0,
            "thumbnail_size": [
                533,
                272
            ],
            "thumbnail_url": "https://addons.mozilla.org/user-media/previews/thumbs/304/304997.jpg?modified=1725825325"
        },
        {
            "id": 304989,
            "caption": {
                "en-US": "Website without (i)frames."
            },
            "image_size": [
                631,
                338
            ],
            "image_url": "https://addons.mozilla.org/user-media/previews/full/304/304989.png?modified=1725825321",
            "position": 1,
            "thumbnail_size": [
                533,
                286
            ],
            "thumbnail_url": "https://addons.mozilla.org/user-media/previews/thumbs/304/304989.jpg?modified=1725825321"
        },
        {
            "id": 304990,
            "caption": {
                "en-US": "Not supported web page."
            },
            "image_size": [
                631,
                338
            ],
            "image_url": "https://addons.mozilla.org/user-media/previews/full/304/304990.png?modified=1725825321",
            "position": 2,
            "thumbnail_size": [
                533,
                286
            ],
            "thumbnail_url": "https://addons.mozilla.org/user-media/previews/thumbs/304/304990.jpg?modified=1725825321"
        },
        {
            "id": 304991,
            "caption": {
                "en-US": "Website with (i)frames to notify."
            },
            "image_size": [
                1174,
                767
            ],
            "image_url": "https://addons.mozilla.org/user-media/previews/full/304/304991.png?modified=1725825321",
            "position": 3,
            "thumbnail_size": [
                533,
                348
            ],
            "thumbnail_url": "https://addons.mozilla.org/user-media/previews/thumbs/304/304991.jpg?modified=1725825321"
        },
        {
            "id": 304993,
            "caption": {
                "en-US": "Website with blacklisted (i)frames."
            },
            "image_size": [
                1174,
                767
            ],
            "image_url": "https://addons.mozilla.org/user-media/previews/full/304/304993.png?modified=1725825321",
            "position": 4,
            "thumbnail_size": [
                533,
                348
            ],
            "thumbnail_url": "https://addons.mozilla.org/user-media/previews/thumbs/304/304993.jpg?modified=1725825321"
        },
        {
            "id": 304992,
            "caption": {
                "en-US": "Website with blacklisted (i)frames. Configuration."
            },
            "image_size": [
                1174,
                767
            ],
            "image_url": "https://addons.mozilla.org/user-media/previews/full/304/304992.png?modified=1725825321",
            "position": 5,
            "thumbnail_size": [
                533,
                348
            ],
            "thumbnail_url": "https://addons.mozilla.org/user-media/previews/thumbs/304/304992.jpg?modified=1725825321"
        },
        {
            "id": 304994,
            "caption": {
                "en-US": "Show logs."
            },
            "image_size": [
                1174,
                767
            ],
            "image_url": "https://addons.mozilla.org/user-media/previews/full/304/304994.png?modified=1725825321",
            "position": 6,
            "thumbnail_size": [
                533,
                348
            ],
            "thumbnail_url": "https://addons.mozilla.org/user-media/previews/thumbs/304/304994.jpg?modified=1725825321"
        },
        {
            "id": 304995,
            "caption": {
                "en-US": "Android add-on. Website with (i)frames."
            },
            "image_size": [
                853,
                1800
            ],
            "image_url": "https://addons.mozilla.org/user-media/previews/full/304/304995.png?modified=1725825321",
            "position": 7,
            "thumbnail_size": [
                189,
                400
            ],
            "thumbnail_url": "https://addons.mozilla.org/user-media/previews/thumbs/304/304995.jpg?modified=1725825321"
        },
        {
            "id": 304996,
            "caption": {
                "en-US": "Android add-on. Menu."
            },
            "image_size": [
                853,
                1800
            ],
            "image_url": "https://addons.mozilla.org/user-media/previews/full/304/304996.png?modified=1725825321",
            "position": 8,
            "thumbnail_size": [
                189,
                400
            ],
            "thumbnail_url": "https://addons.mozilla.org/user-media/previews/thumbs/304/304996.jpg?modified=1725825321"
        }
    ],
    "promoted": null,
    "ratings": {
        "average": 5.0,
        "bayesian_average": 3.7582329233404757,
        "count": 4,
        "text_count": 2
    },
    "ratings_url": "https://addons.mozilla.org/en-US/firefox/addon/check-iframe/reviews/",
    "requires_payment": false,
    "review_url": "https://addons.mozilla.org/en-US/reviewers/review/937315",
    "slug": "check-iframe",
    "status": "public",
    "summary": {
        "en-US": "Firefox add-on that indicates if the current web page uses iframe and frame tags. Icon:\r\n-Gray: not checked.\r\n-Green: no tags.\r\n-Orange: tags.\r\n-Purple: source list matches.\r\nThe  add-on can scroll and redirect to the tag elements."
    },
    "support_email": null,
    "support_url": {
        "url": {
            "en-US": "https://github.com/CarlosAMolina/checkIframe"
        },
        "outgoing": {
            "en-US": "https://prod.outgoing.prod.webservices.mozgcp.net/v1/71afa49e035cbcbe6d517f01c43e9f221dd7bb62d838fdc674aafcd06c7d7935/https%3A//github.com/CarlosAMolina/checkIframe"
        }
    },
    "tags": [],
    "type": "extension",
    "url": "https://addons.mozilla.org/en-US/firefox/addon/check-iframe/",
    "versions_url": "https://addons.mozilla.org/en-US/firefox/addon/check-iframe/versions/",
    "weekly_downloads": 6,
    "_score": null
}